octopyenergy/__init__.py
octopyenergy/api.py
octopyenergy/end_points.json
octopyenergy-0.0.4.dist-info/METADATA
octopyenergy-0.0.4.dist-info/WHEEL
octopyenergy-0.0.4.dist-info/top_level.txt
octopyenergy-0.0.4.dist-info/RECORD
