Metadata-Version: 2.1
Name: octopyenergy
Version: 0.0.4
Summary: Python client for the Octopus energy API
Home-page: https://github.com/AyrtonB/Octopy-Energy
Author: Ayrton Bourn
Author-email: ayrtonbourn@outlook.com
License: UNKNOWN
Platform: UNKNOWN
Classifier: Programming Language :: Python :: 3
Requires-Python: >=3.6
